{
  "server-component": {
    "welcome": "Добро пожаловать!"
  },
  "counter": {
    "increment": "Инкремент",
    "decrement": "Декремент"
  },
  "descr": "WebDevSynergy- це назва, яка яскраво виражає синергію веб-розробки. Він об'єднує Веб (веб) і Dev (збільшення від розробки - розробка) з Синергія (синергія), підчеркуючи спільне та інноваційне розвиток веб-проектів. Компанія з такою назвою може розуміти, що в її основі лежить сильна взаємодія розробників, дизайнерів, маркетологів та інших спеціалістів, щоб створити веб-рішення, які вибрали в себе кращі аспекти кожної області. «WebDevSynergy» може бути зрозумілою як фірма, що стрімко розвивається до творчого, відповідального та спільного підходу до розробки сайтів і додатків."
}
